setup.py
lgraph_cypher.egg-info/PKG-INFO
lgraph_cypher.egg-info/SOURCES.txt
lgraph_cypher.egg-info/dependency_links.txt
lgraph_cypher.egg-info/entry_points.txt
lgraph_cypher.egg-info/requires.txt
lgraph_cypher.egg-info/top_level.txt
lgraph_shell/__init__.py
lgraph_shell/color_format.py
lgraph_shell/db.py
lgraph_shell/lgraph_cypher.py
lgraph_shell/shell_object.py