Metadata-Version: 2.1
Name: lgraph-cypher
Version: 0.0.0
Summary: cypher quarry command line tool for TuGraph
Home-page: UNKNOWN
License: UNKNOWN
Platform: UNKNOWN
